koschei_messages/__init__.py
koschei_messages/base.py
koschei_messages/collection.py
koschei_messages/package.py
koschei_messages-1.0.1.dist-info/entry_points.txt
koschei_messages-1.0.1.dist-info/LICENSES/GPL-2.0-or-later.txt
koschei_messages-1.0.1.dist-info/WHEEL
koschei_messages-1.0.1.dist-info/METADATA
koschei_messages-1.0.1.dist-info/RECORD
